FIPL LICENSE
imageio_freeimage/__init__.py
imageio_freeimage/_freeimage.py
imageio_freeimage/freeimage.py
imageio_freeimage/freeimagemulti.py
LICENSE
imageio_freeimage-0.1.0.dist-info/LICENSE
imageio_freeimage-0.1.0.dist-info/WHEEL
imageio_freeimage-0.1.0.dist-info/METADATA
imageio_freeimage-0.1.0.dist-info/RECORD
